dask_cloudprovider/__init__.py
dask_cloudprovider/_version.py
dask_cloudprovider/cloudprovider.yaml
dask_cloudprovider/config.py
dask_cloudprovider/conftest.py
dask_cloudprovider/exceptions.py
dask_cloudprovider/aws/__init__.py
dask_cloudprovider/aws/ec2.py
dask_cloudprovider/aws/ecs.py
dask_cloudprovider/aws/helper.py
dask_cloudprovider/aws/tests/test_ec2.py
dask_cloudprovider/aws/tests/test_ecs.py
dask_cloudprovider/aws/tests/test_helper.py
dask_cloudprovider/azure/__init__.py
dask_cloudprovider/azure/azurevm.py
dask_cloudprovider/azure/utils.py
dask_cloudprovider/azure/tests/test_azurevm.py
dask_cloudprovider/cli/ecs.py
dask_cloudprovider/digitalocean/__init__.py
dask_cloudprovider/digitalocean/droplet.py
dask_cloudprovider/digitalocean/tests/test_droplet.py
dask_cloudprovider/gcp/__init__.py
dask_cloudprovider/gcp/instances.py
dask_cloudprovider/gcp/utils.py
dask_cloudprovider/gcp/tests/test_gcp.py
dask_cloudprovider/gcp/tests/test_utils.py
dask_cloudprovider/generic/cloud-init.yaml.j2
dask_cloudprovider/generic/vmcluster.py
dask_cloudprovider/generic/tests/test_vmcluster.py
dask_cloudprovider/hetzner/__init__.py
dask_cloudprovider/hetzner/vserver.py
dask_cloudprovider/hetzner/tests/test_vserver.py
dask_cloudprovider/ibm/__init__.py
dask_cloudprovider/ibm/code_engine.py
dask_cloudprovider/ibm/tests/test_code_engine.py
dask_cloudprovider/nebius/__init__.py
dask_cloudprovider/nebius/instances.py
dask_cloudprovider/nebius/tests/test_nebius.py
dask_cloudprovider/openstack/__init__.py
dask_cloudprovider/openstack/instances.py
dask_cloudprovider/openstack/tests/test_instances.py
dask_cloudprovider/tests/test_imports.py
dask_cloudprovider/utils/config_helper.py
dask_cloudprovider/utils/logs.py
dask_cloudprovider/utils/socket.py
dask_cloudprovider/utils/timeout.py
dask_cloudprovider/utils/tests/test_config_helper.py
dask_cloudprovider-2025.9.0.dist-info/licenses/LICENSE
dask_cloudprovider-2025.9.0.dist-info/METADATA
dask_cloudprovider-2025.9.0.dist-info/WHEEL
dask_cloudprovider-2025.9.0.dist-info/entry_points.txt
dask_cloudprovider-2025.9.0.dist-info/top_level.txt
dask_cloudprovider-2025.9.0.dist-info/RECORD
