Metadata-Version: 2.4
Name: dask-cloudprovider
Version: 2025.9.0
Summary: Native Cloud Provider integration for Dask
Home-page: https://github.com/dask/dask-cloudprovider
License: BSD
Keywords: dask,cloud,distributed
Requires-Python: >=3.10
License-File: LICENSE
Requires-Dist: aiohttp>=3.7.3
Requires-Dist: dask>=2021.01.1
Requires-Dist: distributed>=2021.01.1
Requires-Dist: jinja2
Requires-Dist: tornado>=5
Provides-Extra: aws
Requires-Dist: aiobotocore>=0.10.2; extra == "aws"
Provides-Extra: azure
Requires-Dist: azure-mgmt-compute>=18.0.0; extra == "azure"
Requires-Dist: azure-mgmt-network>=16.0.0; extra == "azure"
Requires-Dist: azure-identity; extra == "azure"
Provides-Extra: digitalocean
Requires-Dist: python-digitalocean>=1.15.0; extra == "digitalocean"
Provides-Extra: gcp
Requires-Dist: google-api-python-client>=1.12.5; extra == "gcp"
Requires-Dist: google-auth>=1.23.0; extra == "gcp"
Provides-Extra: hetzner
Requires-Dist: hcloud>=1.10.0; extra == "hetzner"
Provides-Extra: ibm
Requires-Dist: ibm_code_engine_sdk>=3.1.0; extra == "ibm"
Requires-Dist: kubernetes>=25.3.0; extra == "ibm"
Provides-Extra: openstack
Requires-Dist: openstacksdk>=3.3.0; extra == "openstack"
Provides-Extra: nebius
Requires-Dist: nebius>=0.2.0; extra == "nebius"
Provides-Extra: all
Requires-Dist: azure-mgmt-network>=16.0.0; extra == "all"
Requires-Dist: google-api-python-client>=1.12.5; extra == "all"
Requires-Dist: nebius>=0.2.0; extra == "all"
Requires-Dist: python-digitalocean>=1.15.0; extra == "all"
Requires-Dist: hcloud>=1.10.0; extra == "all"
Requires-Dist: kubernetes>=25.3.0; extra == "all"
Requires-Dist: openstacksdk>=3.3.0; extra == "all"
Requires-Dist: ibm_code_engine_sdk>=3.1.0; extra == "all"
Requires-Dist: azure-mgmt-compute>=18.0.0; extra == "all"
Requires-Dist: google-auth>=1.23.0; extra == "all"
Requires-Dist: azure-identity; extra == "all"
Requires-Dist: aiobotocore>=0.10.2; extra == "all"
Dynamic: description
Dynamic: description-content-type
Dynamic: home-page
Dynamic: keywords
Dynamic: license
Dynamic: license-file
Dynamic: provides-extra
Dynamic: requires-dist
Dynamic: requires-python
Dynamic: summary
